{"name":"Terra Valentine","url":"http://www.napavintners.com/winery/terra-valentine/","logo":"http://www.napavintners.org/images/winery_labels/Valentine-105HW.jpg","region":"Napa","address":{"street":"264 North Crystal Springs Road","city":"Saint Helena","stateOrProvince":"CA","postalCode":"94574","country":"USA"},"phone":" |","email":"info@terravalentine.com","website":"http://www.terravalentine.com?utm_source=napavintners.com&utm_medium=website&utm_campaign=WineryListing","social":{"facebook":"http://www.facebook.com/search.php?q=Terra+Valentine+Winery&init=quick#!/pages/Terra-Valentine-Winery/15321095532","twitter":"http://twitter.com/terravalentine","youtube":"http://www.youtube.com/user/TerraValentine"},"varietals":["Cabernet Franc","Cabernet Sauvignon","Merlot","Pinot Noir","Red Blend","Riesling","Sangiovese","Sauvignon Blanc","Syrah","Viognier"],"appelations":["Atlas Peak","Napa Valley","Spring Mountain"]}