{"name":"Boeschen Vineyards","url":"http://www.napavintners.com/vineyards/boeschen-vineyards/","logo":"http://www.napavintners.org/images/winery_labels/boeschen-105HW.jpg","region":"Napa","address":{"street":"3242 Silverado Trail North","city":"Saint Helena","stateOrProvince":"CA","postalCode":"94574","country":"USA"},"phone":" |","email":"info@boeschenvineyards.com","website":"http://www.boeschenvineyards.com?utm_source=napavintners.com&utm_medium=website&utm_campaign=WineryListing","social":{},"varietals":["Cabernet Franc","Cabernet Sauvignon","Malbec","Merlot","Petit Verdot","Sauvignon Blanc"],"appelations":["St. Helena"]}